temp_interpolation/__init__.py
temp_interpolation/common.py
temp_interpolation/foliummap.py
temp_interpolation/temp_interpolation.py
temp_interpolation-0.1.1.dist-info/licenses/LICENSE
temp_interpolation-0.1.1.dist-info/METADATA
temp_interpolation-0.1.1.dist-info/WHEEL
temp_interpolation-0.1.1.dist-info/entry_points.txt
temp_interpolation-0.1.1.dist-info/top_level.txt
temp_interpolation-0.1.1.dist-info/RECORD
