Metadata-Version: 2.4
Name: temp_interpolation
Version: 0.1.1
Summary: A package for temporal interpolation of spatial data
Author-email: Ishwar Nalawade <ishwarn93@gmail.com>
License: MIT License
Project-URL: Homepage, https://github.com/ishwar97/temp_interpolation
Keywords: temp_interpolation
Classifier: Intended Audience :: Developers
Classifier: License :: OSI Approved :: MIT License
Classifier: Natural Language :: English
Classifier: Programming Language :: Python :: 3.8
Classifier: Programming Language :: Python :: 3.9
Classifier: Programming Language :: Python :: 3.10
Classifier: Programming Language :: Python :: 3.11
Classifier: Programming Language :: Python :: 3.12
Requires-Python: >=3.8
License-File: LICENSE
Requires-Dist: folium
Requires-Dist: geopandas
Requires-Dist: ipyleaflet
Requires-Dist: localtileserver
Requires-Dist: matplotlib
Requires-Dist: numpy
Requires-Dist: rasterio
Requires-Dist: requests
Provides-Extra: all
Requires-Dist: temp_interpolation[extra]; extra == "all"
Provides-Extra: extra
Requires-Dist: pandas; extra == "extra"
Dynamic: license-file
